griottes/__init__.py
griottes/_version.py
griottes/analyse/__init__.py
griottes/analyse/cell_property_extraction.py
griottes/analyse/voronoi_cell_property_analysis.py
griottes/graphmaker/__init__.py
griottes/graphmaker/graph_generation_func.py
griottes/graphmaker/make_spheroids.py
griottes/graphplotter/__init__.py
griottes/graphplotter/graph_plot.py
griottes/tests/__init__.py
griottes/tests/test_analyse.py
griottes/tests/test_graphmaker.py
griottes-0.1.1.dist-info/LICENSE
griottes-0.1.1.dist-info/METADATA
griottes-0.1.1.dist-info/WHEEL
griottes-0.1.1.dist-info/top_level.txt
griottes-0.1.1.dist-info/RECORD
