Metadata-Version: 2.1
Name: griottes
Version: 0.1.1
Summary: Python program to generate NetworkX graphs from segmented images
Author: 
Requires-Dist: numpy
Requires-Dist: scipy
Requires-Dist: networkx
Requires-Dist: tqdm
Requires-Dist: pandas
Requires-Dist: scikit-image
Requires-Dist: scikit-learn
Requires-Dist: matplotlib
Requires-Dist: seaborn
